{
  "scraped_at": "2026-07-20T19:03:59.629Z",
  "brand_name": "Al Qasim Oud",
  "brand_slug": "Al-Qasim-Oud",
  "brand_url": "https://www.fragrantica.com/designers/Al-Qasim-Oud.html",
  "fragrances": [
    {
      "name": "Al Qasim Oud",
      "url": "https://www.fragrantica.com/perfume/Al-Qasim-Oud/BLACK-ROSE-119463.html",
      "img": "https://fimgs.net/mdimg/perfume-thumbs/m.119463.jpg",
      "rating": null,
      "votes": 0
    },
    {
      "name": "Al Qasim Oud",
      "url": "https://www.fragrantica.com/perfume/Al-Qasim-Oud/MARVEL-119458.html",
      "img": "https://fimgs.net/mdimg/perfume-thumbs/m.119458.jpg",
      "rating": null,
      "votes": 0
    },
    {
      "name": "Al Qasim Oud",
      "url": "https://www.fragrantica.com/perfume/Al-Qasim-Oud/MIXED-LEATHER-119462.html",
      "img": "https://fimgs.net/mdimg/perfume-thumbs/m.119462.jpg",
      "rating": null,
      "votes": 0
    },
    {
      "name": "Al Qasim Oud",
      "url": "https://www.fragrantica.com/perfume/Al-Qasim-Oud/MIZAH-119461.html",
      "img": "https://fimgs.net/mdimg/perfume-thumbs/m.119461.jpg",
      "rating": null,
      "votes": 0
    },
    {
      "name": "Al Qasim Oud",
      "url": "https://www.fragrantica.com/perfume/Al-Qasim-Oud/OUD-MONREALE-119460.html",
      "img": "https://fimgs.net/mdimg/perfume-thumbs/m.119460.jpg",
      "rating": null,
      "votes": 0
    },
    {
      "name": "Al Qasim Oud",
      "url": "https://www.fragrantica.com/perfume/Al-Qasim-Oud/RAZAH-119464.html",
      "img": "https://fimgs.net/mdimg/perfume-thumbs/m.119464.jpg",
      "rating": null,
      "votes": 0
    },
    {
      "name": "Al Qasim Oud",
      "url": "https://www.fragrantica.com/perfume/Al-Qasim-Oud/VELAN-119459.html",
      "img": "https://fimgs.net/mdimg/perfume-thumbs/m.119459.jpg",
      "rating": null,
      "votes": 0
    },
    {
      "name": "Al Qasim Oud",
      "url": "https://www.fragrantica.com/perfume/Al-Qasim-Oud/BONITA-White-Hair-Mist-119739.html",
      "img": "https://fimgs.net/mdimg/perfume-thumbs/m.119739.jpg",
      "rating": null,
      "votes": 0
    },
    {
      "name": "Al Qasim Oud",
      "url": "https://www.fragrantica.com/perfume/Al-Qasim-Oud/DANTY-Green-Hair-Mist-119737.html",
      "img": "https://fimgs.net/mdimg/perfume-thumbs/m.119737.jpg",
      "rating": null,
      "votes": 0
    },
    {
      "name": "Al Qasim Oud",
      "url": "https://www.fragrantica.com/perfume/Al-Qasim-Oud/MARTA-Brown-Hair-Mist-119736.html",
      "img": "https://fimgs.net/mdimg/perfume-thumbs/m.119736.jpg",
      "rating": null,
      "votes": 0
    }
  ]
}