{
  "scraped_at": "2026-07-20T18:48:51.081Z",
  "brand_name": "Beija Fine Perfumes",
  "brand_slug": "Beija-Fine-Perfumes",
  "brand_url": "https://www.fragrantica.com/designers/Beija-Fine-Perfumes.html",
  "fragrances": [
    {
      "name": "Beija Fine Perfumes",
      "url": "https://www.fragrantica.com/perfume/Beija-Fine-Perfumes/52nd-Bebop-The-Pirates-Amber-119556.html",
      "img": "https://fimgs.net/mdimg/perfume-thumbs/m.119556.jpg",
      "rating": null,
      "votes": 0
    },
    {
      "name": "Beija Fine Perfumes",
      "url": "https://www.fragrantica.com/perfume/Beija-Fine-Perfumes/Dark-Cherry-Reserve-119554.html",
      "img": "https://fimgs.net/mdimg/perfume-thumbs/m.119554.jpg",
      "rating": null,
      "votes": 0
    },
    {
      "name": "Beija Fine Perfumes",
      "url": "https://www.fragrantica.com/perfume/Beija-Fine-Perfumes/Oudh-Beija-Grapevine-119552.html",
      "img": "https://fimgs.net/mdimg/perfume-thumbs/m.119552.jpg",
      "rating": null,
      "votes": 0
    },
    {
      "name": "Beija Fine Perfumes",
      "url": "https://www.fragrantica.com/perfume/Beija-Fine-Perfumes/Dreams-of-Tuscany-Medieval-Borgo-119560.html",
      "img": "https://fimgs.net/mdimg/perfume-thumbs/m.119560.jpg",
      "rating": null,
      "votes": 0
    },
    {
      "name": "Beija Fine Perfumes",
      "url": "https://www.fragrantica.com/perfume/Beija-Fine-Perfumes/Sounds-of-Summer-Taormina-Sicily-119557.html",
      "img": "https://fimgs.net/mdimg/perfume-thumbs/m.119557.jpg",
      "rating": null,
      "votes": 0
    },
    {
      "name": "Beija Fine Perfumes",
      "url": "https://www.fragrantica.com/perfume/Beija-Fine-Perfumes/Vanilla-Dust-and-The-Library-119559.html",
      "img": "https://fimgs.net/mdimg/perfume-thumbs/m.119559.jpg",
      "rating": null,
      "votes": 0
    },
    {
      "name": "Bargello",
      "url": "https://www.fragrantica.com/perfume/Bargello/Fleur-De-Perle-132951.html",
      "img": "https://fimgs.net/mdimg/perfume-thumbs/m.132951.jpg",
      "rating": null,
      "votes": 0
    },
    {
      "name": "Yves Saint Laurent",
      "url": "https://www.fragrantica.com/perfume/Yves-Saint-Laurent/MYSLF-L-Absolu-107428.html",
      "img": "https://fimgs.net/mdimg/perfume-thumbs/m.107428.jpg",
      "rating": null,
      "votes": 0
    },
    {
      "name": "Serge Lutens",
      "url": "https://www.fragrantica.com/perfume/Serge-Lutens/La-Fille-de-Berlin-17162.html",
      "img": "https://fimgs.net/mdimg/perfume-thumbs/m.17162.jpg",
      "rating": null,
      "votes": 0
    },
    {
      "name": "Bargello",
      "url": "https://www.fragrantica.com/perfume/Bargello/Vega-133081.html",
      "img": "https://fimgs.net/mdimg/perfume-thumbs/m.133081.jpg",
      "rating": null,
      "votes": 0
    }
  ]
}