{
  "scraped_at": "2026-07-20T18:40:26.631Z",
  "brand_name": "Maison Alhambra",
  "brand_slug": "Maison-Alhambra",
  "brand_url": "https://www.fragrantica.com/designers/Maison-Alhambra.html",
  "fragrances": [
    {
      "name": "Maison Alhambra",
      "url": "https://www.fragrantica.com/perfume/Maison-Alhambra/05-Domino-Essence-95503.html",
      "img": "https://fimgs.net/mdimg/perfume-thumbs/m.95503.jpg",
      "rating": null,
      "votes": 0
    },
    {
      "name": "Maison Alhambra",
      "url": "https://www.fragrantica.com/perfume/Maison-Alhambra/Afro-Leather-95267.html",
      "img": "https://fimgs.net/mdimg/perfume-thumbs/m.95267.jpg",
      "rating": null,
      "votes": 0
    },
    {
      "name": "Maison Alhambra",
      "url": "https://www.fragrantica.com/perfume/Maison-Alhambra/Alive-Now-111234.html",
      "img": "https://fimgs.net/mdimg/perfume-thumbs/m.111234.jpg",
      "rating": null,
      "votes": 0
    },
    {
      "name": "Maison Alhambra",
      "url": "https://www.fragrantica.com/perfume/Maison-Alhambra/Alpine-Homme-Sport-83311.html",
      "img": "https://fimgs.net/mdimg/perfume-thumbs/m.83311.jpg",
      "rating": null,
      "votes": 0
    },
    {
      "name": "Maison Alhambra",
      "url": "https://www.fragrantica.com/perfume/Maison-Alhambra/Amber-Leather-93661.html",
      "img": "https://fimgs.net/mdimg/perfume-thumbs/m.93661.jpg",
      "rating": null,
      "votes": 0
    },
    {
      "name": "Maison Alhambra",
      "url": "https://www.fragrantica.com/perfume/Maison-Alhambra/Amberley-Ombre-Blue-94167.html",
      "img": "https://fimgs.net/mdimg/perfume-thumbs/m.94167.jpg",
      "rating": null,
      "votes": 0
    },
    {
      "name": "Maison Alhambra",
      "url": "https://www.fragrantica.com/perfume/Maison-Alhambra/Amberley-Pur-Oud-95504.html",
      "img": "https://fimgs.net/mdimg/perfume-thumbs/m.95504.jpg",
      "rating": null,
      "votes": 0
    },
    {
      "name": "Maison Alhambra",
      "url": "https://www.fragrantica.com/perfume/Maison-Alhambra/Amberly-Amoroso-94160.html",
      "img": "https://fimgs.net/mdimg/perfume-thumbs/m.94160.jpg",
      "rating": null,
      "votes": 0
    },
    {
      "name": "Maison Alhambra",
      "url": "https://www.fragrantica.com/perfume/Maison-Alhambra/Anarch-82382.html",
      "img": "https://fimgs.net/mdimg/perfume-thumbs/m.82382.jpg",
      "rating": null,
      "votes": 0
    },
    {
      "name": "Maison Alhambra",
      "url": "https://www.fragrantica.com/perfume/Maison-Alhambra/Anchor-Black-93851.html",
      "img": "https://fimgs.net/mdimg/perfume-thumbs/m.93851.jpg",
      "rating": null,
      "votes": 0
    }
  ]
}