{"name":"Fila","slug":"fila","products":[{"name":"Fila Black Perfume For Men EDT 100ml","brand":"Fila","handle":"fila-black-perfume-for-men-edt-100ml","img":"https://cdn.shopify.com/s/files/1/0573/6241/5800/files/41_MDCMxd0S._SL1500.jpg?v=1751652217","price_gros":65,"price_retail":65,"badge":"","category_slug":"homme","size":"100ml","tags":["100ml","Branded Perfumes","EDT","Fragrance","Men"],"product_url":"https://samawa.ae/products/fila-black-perfume-for-men-edt-100ml","sku":"843711294616"},{"name":"Fila for Men, 100 ml - EDT Spray","brand":"Fila","handle":"fila-for-men-100-ml-edt-spray","img":"https://cdn.shopify.com/s/files/1/0573/6241/5800/products/fila_for_men_100_ml_-_edt_spray...jpg?v=1624474142","price_gros":66,"price_retail":66,"badge":"","category_slug":"homme","size":"100ml","tags":["100ml","Branded Perfumes","EDT","Fragrance","Men"],"product_url":"https://samawa.ae/products/fila-for-men-100-ml-edt-spray","sku":"843711121325"}]}